resmali/__init__.py
resmali/resmali.py
resmali-0.1.0.dist-info/METADATA
resmali-0.1.0.dist-info/WHEEL
resmali-0.1.0.dist-info/licenses/LICENSE
resmali-0.1.0.dist-info/RECORD
