Metadata-Version: 2.1
Name: resmali
Version: 0.1.0
Summary: Scoring matrix-assisted ligand identification (SMALI) rewritten.
Project-URL: Homepage, https://github.com/DT-Newman/reSMALI
Author-email: Daniel Newman <24903676+DT-Newman@users.noreply.github.com>
License-File: LICENSE
Classifier: License :: OSI Approved :: GNU General Public License v3 (GPLv3)
Classifier: Operating System :: OS Independent
Classifier: Programming Language :: Python :: 3
Requires-Python: >=3.7
